fangcloud_mcp/__init__.py
fangcloud_mcp/fangcloud.py
fangcloud_mcp/fangcloud_api.py
fangcloud_mcp-0.1.7.dist-info/METADATA
fangcloud_mcp-0.1.7.dist-info/WHEEL
fangcloud_mcp-0.1.7.dist-info/entry_points.txt
fangcloud_mcp-0.1.7.dist-info/licenses/LICENSE
fangcloud_mcp-0.1.7.dist-info/RECORD
