Metadata-Version: 2.4
Name: fangcloud-mcp
Version: 0.1.7
Summary: FangCloud MCP 是一个 Model Context Protocol (MCP) 服务器实现，提供与 FangCloud 云存储服务的集成
License-File: LICENSE
Requires-Python: >=3.12
Requires-Dist: aiohttp>=3.8.6
Requires-Dist: mcp[cli]>=1.7.1
